gllm_multimodal.cpython-312-x86_64-linux-gnu.so
gllm_multimodal.pyi
gllm_multimodal/__init__.pyi
gllm_multimodal/constants.pyi
gllm_multimodal/builder/__init__.pyi
gllm_multimodal/builder/modality_converter_builder.pyi
gllm_multimodal/modality_converter/__init__.pyi
gllm_multimodal/modality_converter/modality_converter.pyi
gllm_multimodal/modality_converter/audio_to_text/__init__.pyi
gllm_multimodal/modality_converter/audio_to_text/audio_to_text.pyi
gllm_multimodal/modality_converter/audio_to_text/gemini_audio_to_text.pyi
gllm_multimodal/modality_converter/audio_to_text/google_cloud_audio_to_text.pyi
gllm_multimodal/modality_converter/audio_to_text/openai_whisper_audio_to_text.pyi
gllm_multimodal/modality_converter/audio_to_text/prosa_audio_to_text.pyi
gllm_multimodal/modality_converter/audio_to_text/youtube_transcript_audio_to_text.pyi
gllm_multimodal/modality_converter/image_to_text/__init__.pyi
gllm_multimodal/modality_converter/image_to_text/image_to_text.pyi
gllm_multimodal/modality_converter/image_to_text/image_to_caption/__init__.pyi
gllm_multimodal/modality_converter/image_to_text/image_to_caption/image_to_caption.pyi
gllm_multimodal/modality_converter/image_to_text/image_to_caption/lm_based_image_to_caption.pyi
gllm_multimodal/modality_converter/image_to_text/image_to_caption/preset_image_to_caption.pyi
gllm_multimodal/modality_converter/image_to_text/image_to_mermaid/__init__.pyi
gllm_multimodal/modality_converter/image_to_text/image_to_mermaid/image_to_mermaid.pyi
gllm_multimodal/modality_converter/image_to_text/image_to_mermaid/lm_based_image_to_mermaid.pyi
gllm_multimodal/modality_converter/image_to_text/image_to_mermaid/preset_image_to_mermaid.pyi
gllm_multimodal/modality_converter/schema/__init__.pyi
gllm_multimodal/modality_converter/schema/audio_transcript.pyi
gllm_multimodal/modality_converter/schema/caption.pyi
gllm_multimodal/modality_converter/schema/mermaid.pyi
gllm_multimodal/modality_converter/schema/text_result.pyi
gllm_multimodal_binary-0.3.1.post2.dist-info/METADATA
gllm_multimodal_binary-0.3.1.post2.dist-info/WHEEL
gllm_multimodal_binary-0.3.1.post2.dist-info/top_level.txt
gllm_multimodal_binary-0.3.1.post2.dist-info/RECORD
